laoshu/__init__.py
laoshu/baml_client/__init__.py
laoshu/baml_client/async_client.py
laoshu/baml_client/async_request.py
laoshu/baml_client/config.py
laoshu/baml_client/globals.py
laoshu/baml_client/inlinedbaml.py
laoshu/baml_client/parser.py
laoshu/baml_client/partial_types.py
laoshu/baml_client/sync_client.py
laoshu/baml_client/sync_request.py
laoshu/baml_client/tracing.py
laoshu/baml_client/type_builder.py
laoshu/baml_client/types.py
laoshu/clustering/__init__.py
laoshu/clustering/clustering.py
laoshu/clustering/embeddings.py
laoshu/clustering/grouping.py
laoshu/clustering/topic_modeling.py
laoshu/commands/__init__.py
laoshu/commands/cluster_prompts.py
laoshu/config/__init__.py
laoshu/config/dotenv.py
laoshu/config/logger.py
laoshu/data/__init__.py
laoshu/data/definitions.py
laoshu/data/external_data_definitions.py
laoshu/data/loaders/__init__.py
laoshu/data/loaders/json_loader.py
laoshu/data/savers/__init__.py
laoshu/data/savers/json_saver.py
laoshu/display/__init__.py
laoshu/display/progress.py
laoshu/display/show_output.py
laoshu/prompts/__init__.py
laoshu/prompts/template_renderer.py
laoshu-0.1.0.dist-info/LICENSE.md
laoshu-0.1.0.dist-info/METADATA
laoshu-0.1.0.dist-info/WHEEL
laoshu-0.1.0.dist-info/entry_points.txt
laoshu-0.1.0.dist-info/RECORD
