Metadata-Version: 2.3
Name: laoshu
Version: 0.1.0
Summary: Automatic hallucination classification and prompt improvement
Author: Bartosz Mikulski
Requires-Python: >=3.12
Classifier: Programming Language :: Python :: 3
Classifier: Programming Language :: Python :: 3.12
Classifier: Programming Language :: Python :: 3.13
Requires-Dist: baml-py (==0.87.2)
Requires-Dist: click (==8.2.0)
Requires-Dist: openai (==1.77.0)
Requires-Dist: pydantic (==2.11.4)
Requires-Dist: rich (==14.0.0)
Requires-Dist: scikit-learn (==1.6.1)
